{
	"_comment": "Created by Steven Shrewsbury (stshrewsburyDev)",
	"textures": {
		"wood_sword": "./aotj_handle",
		"farmer": "./aotj_villager"
	},
	"elements": [
		{
			"name": "hilt_1",
			"from": [7, 0, 7.5],
			"to": [8, 3, 8.5],
			"rotation": {"angle": -45, "axis": "z", "origin": [8, 0, 8]},
			"faces": {
				"north": {"uv": [0, 13, 1, 16], "texture": "#wood_sword"},
				"east": {"uv": [0, 13, 1, 16], "texture": "#wood_sword"},
				"south": {"uv": [0, 13, 1, 16], "texture": "#wood_sword"},
				"west": {"uv": [0, 13, 1, 16], "texture": "#wood_sword"},
				"up": {"uv": [0, 15, 1, 16], "texture": "#wood_sword"},
				"down": {"uv": [0, 15, 1, 16], "texture": "#wood_sword"}
			}
		},
		{
			"name": "hilt_2",
			"from": [5, 0, 7.5],
			"to": [6, 3, 8.5],
			"rotation": {"angle": -45, "axis": "z", "origin": [8, 0, 8]},
			"faces": {
				"north": {"uv": [0, 13, 1, 16], "texture": "#wood_sword"},
				"east": {"uv": [0, 13, 1, 16], "texture": "#wood_sword"},
				"south": {"uv": [0, 13, 1, 16], "texture": "#wood_sword"},
				"west": {"uv": [0, 13, 1, 16], "texture": "#wood_sword"},
				"up": {"uv": [0, 15, 1, 16], "texture": "#wood_sword"},
				"down": {"uv": [0, 15, 1, 16], "texture": "#wood_sword"}
			}
		},
		{
			"name": "hilt_3",
			"from": [6, 0, 7.5],
			"to": [7, 1, 8.5],
			"rotation": {"angle": -45, "axis": "z", "origin": [8, 0, 8]},
			"faces": {
				"north": {"uv": [0, 15, 1, 16], "texture": "#wood_sword"},
				"east": {"uv": [0, 15, 1, 16], "texture": "#wood_sword"},
				"south": {"uv": [0, 15, 1, 16], "texture": "#wood_sword"},
				"west": {"uv": [0, 15, 1, 16], "texture": "#wood_sword"},
				"up": {"uv": [0, 15, 1, 16], "texture": "#wood_sword"},
				"down": {"uv": [0, 15, 1, 16], "texture": "#wood_sword"}
			}
		},
		{
			"name": "hilt_4",
			"from": [6, 2, 7.5],
			"to": [7, 3, 8.5],
			"rotation": {"angle": -45, "axis": "z", "origin": [8, 0, 8]},
			"faces": {
				"north": {"uv": [0, 15, 1, 16], "texture": "#wood_sword"},
				"east": {"uv": [0, 15, 1, 16], "texture": "#wood_sword"},
				"south": {"uv": [0, 15, 1, 16], "texture": "#wood_sword"},
				"west": {"uv": [0, 15, 1, 16], "texture": "#wood_sword"},
				"up": {"uv": [0, 15, 1, 16], "texture": "#wood_sword"},
				"down": {"uv": [0, 15, 1, 16], "texture": "#wood_sword"}
			}
		},
		{
			"name": "hilt_center",
			"from": [6, 1, 7.6],
			"to": [7, 2, 8.4],
			"rotation": {"angle": -45, "axis": "z", "origin": [8, 0, 8]},
			"faces": {
				"north": {"uv": [1, 14, 2, 15], "texture": "#wood_sword"},
				"east": {"uv": [1, 14, 1.8, 15], "texture": "#wood_sword"},
				"south": {"uv": [1, 14, 2, 15], "texture": "#wood_sword"},
				"west": {"uv": [1, 14, 1.8, 15], "texture": "#wood_sword"},
				"up": {"uv": [1, 14, 2, 14.8], "texture": "#wood_sword"},
				"down": {"uv": [1, 14, 2, 14.8], "texture": "#wood_sword"}
			}
		},
		{
			"name": "grip_0",
			"from": [4, 2, 7.9],
			"to": [6, 4, 8.1],
			"rotation": {"angle": -45, "axis": "z", "origin": [8, 0, 8]},
			"faces": {
				"north": {"uv": [2, 12, 4, 14], "texture": "#wood_sword"},
				"east": {"uv": [2, 13, 4, 13.2], "rotation": 270, "texture": "#wood_sword"},
				"south": {"uv": [2, 12, 4, 14], "rotation": 270, "texture": "#wood_sword"},
				"west": {"uv": [2, 12, 4, 13], "rotation": 270, "texture": "#wood_sword"},
				"up": {"uv": [3, 12, 4, 14], "rotation": 270, "texture": "#wood_sword"},
				"down": {"uv": [2, 12, 2.2, 14], "rotation": 270, "texture": "#wood_sword"}
			}
		},
		{
			"name": "grip_1",
			"from": [3, 3, 7.9],
			"to": [5, 5, 8.1],
			"rotation": {"angle": -45, "axis": "z", "origin": [8, 0, 8]},
			"faces": {
				"north": {"uv": [3, 11, 5, 13], "texture": "#wood_sword"},
				"east": {"uv": [3, 12, 5, 12.2], "rotation": 270, "texture": "#wood_sword"},
				"south": {"uv": [3, 11, 5, 13], "rotation": 270, "texture": "#wood_sword"},
				"west": {"uv": [3, 11, 5, 11.2], "rotation": 270, "texture": "#wood_sword"},
				"up": {"uv": [4, 11, 4.2, 13], "rotation": 270, "texture": "#wood_sword"},
				"down": {"uv": [3, 11, 3.2, 13], "rotation": 270, "texture": "#wood_sword"}
			}
		},
		{
			"name": "grip_2",
			"from": [4, 3, 7.8],
			"to": [5, 4, 8.2],
			"rotation": {"angle": -45, "axis": "z", "origin": [8, 0, 8]},
			"faces": {
				"north": {"uv": [3, 12, 4, 13], "texture": "#wood_sword"},
				"east": {"uv": [3, 12, 3.4, 13], "texture": "#wood_sword"},
				"south": {"uv": [3, 12, 4, 13], "texture": "#wood_sword"},
				"west": {"uv": [3, 12, 3.4, 13], "texture": "#wood_sword"},
				"up": {"uv": [3, 12, 4, 12.4], "texture": "#wood_sword"},
				"down": {"uv": [3, 12, 4, 12.4], "texture": "#wood_sword"}
			}
		},
		{
			"name": "grip_3",
			"from": [3, 4, 7.8],
			"to": [4, 5, 8.2],
			"rotation": {"angle": -45, "axis": "z", "origin": [8, 0, 8]},
			"faces": {
				"north": {"uv": [4, 11, 5, 12], "texture": "#wood_sword"},
				"east": {"uv": [4, 11, 4.4, 12], "texture": "#wood_sword"},
				"south": {"uv": [4, 11, 5, 12], "texture": "#wood_sword"},
				"west": {"uv": [4, 11, 4.4, 12], "texture": "#wood_sword"},
				"up": {"uv": [4, 11, 5, 11.4], "texture": "#wood_sword"},
				"down": {"uv": [4, 11, 5, 11.4], "texture": "#wood_sword"}
			}
		},
		{
			"name": "guard_0",
			"from": [2, 4, 7.7],
			"to": [3, 5, 8.3],
			"rotation": {"angle": -45, "axis": "z", "origin": [8, 0, 8]},
			"faces": {
				"north": {"uv": [5, 11, 6, 12], "texture": "#wood_sword"},
				"east": {"uv": [5, 11, 5.6, 12], "texture": "#wood_sword"},
				"south": {"uv": [5, 11, 6, 12], "texture": "#wood_sword"},
				"west": {"uv": [5, 11, 5.6, 12], "texture": "#wood_sword"},
				"up": {"uv": [5, 11, 6, 11.6], "texture": "#wood_sword"},
				"down": {"uv": [5, 11, 6, 11.6], "texture": "#wood_sword"}
			}
		},
		{
			"name": "guard_1",
			"from": [3, 5, 7.7],
			"to": [4, 6, 8.3],
			"rotation": {"angle": -45, "axis": "z", "origin": [8, 0, 8]},
			"faces": {
				"north": {"uv": [4, 10, 5, 11], "texture": "#wood_sword"},
				"east": {"uv": [4, 10, 4.6, 11], "texture": "#wood_sword"},
				"south": {"uv": [4, 10, 5, 11], "texture": "#wood_sword"},
				"west": {"uv": [4, 10, 4.6, 11], "texture": "#wood_sword"},
				"up": {"uv": [4, 10, 5, 10.6], "texture": "#wood_sword"},
				"down": {"uv": [4, 10, 5, 10.6], "texture": "#wood_sword"}
			}
		},
		{
			"name": "guard_2",
			"from": [0, 3, 7.7],
			"to": [2, 4, 8.3],
			"rotation": {"angle": -45, "axis": "z", "origin": [8, 0, 8]},
			"faces": {
				"north": {"uv": [6, 12, 8, 13], "texture": "#wood_sword"},
				"east": {"uv": [6, 12, 6.6, 13], "texture": "#wood_sword"},
				"south": {"uv": [6, 12, 8, 13], "texture": "#wood_sword"},
				"west": {"uv": [7, 12, 7.6, 13], "texture": "#wood_sword"},
				"up": {"uv": [6, 12, 8, 12.6], "texture": "#wood_sword"},
				"down": {"uv": [6, 12, 8, 12.6], "texture": "#wood_sword"}
			}
		},
		{
			"name": "guard_3",
			"from": [4, 6, 7.7],
			"to": [5, 8, 8.3],
			"rotation": {"angle": -45, "axis": "z", "origin": [8, 0, 8]},
			"faces": {
				"north": {"uv": [3, 8, 4, 10], "texture": "#wood_sword"},
				"east": {"uv": [3, 8, 3.6, 10], "texture": "#wood_sword"},
				"south": {"uv": [3, 8, 4, 10], "texture": "#wood_sword"},
				"west": {"uv": [3, 8, 3.6, 10], "texture": "#wood_sword"},
				"up": {"uv": [3, 8, 4, 8.6], "texture": "#wood_sword"},
				"down": {"uv": [3, 9, 4, 9.6], "texture": "#wood_sword"}
			}
		},
		{
			"name": "guard_4",
			"from": [-2, 2, 7.7],
			"to": [0, 3, 8.3],
			"rotation": {"angle": -45, "axis": "z", "origin": [8, 0, 8]},
			"faces": {
				"north": {"uv": [8, 13, 10, 14], "texture": "#wood_sword"},
				"east": {"uv": [8, 13, 8.6, 14], "texture": "#wood_sword"},
				"south": {"uv": [8, 13, 10, 14], "texture": "#wood_sword"},
				"west": {"uv": [9, 13, 9.6, 14], "texture": "#wood_sword"},
				"up": {"uv": [8, 13, 10, 13.6], "texture": "#wood_sword"},
				"down": {"uv": [8, 13, 10, 13.6], "texture": "#wood_sword"}
			}
		},
		{
			"name": "guard_5",
			"from": [-2, 3, 7.7],
			"to": [-1, 4, 8.3],
			"rotation": {"angle": -45, "axis": "z", "origin": [8, 0, 8]},
			"faces": {
				"north": {"uv": [9, 12, 10, 13], "texture": "#wood_sword"},
				"east": {"uv": [9, 12, 9.6, 13], "texture": "#wood_sword"},
				"south": {"uv": [9, 12, 10, 13], "texture": "#wood_sword"},
				"west": {"uv": [9, 12, 9.6, 13], "texture": "#wood_sword"},
				"up": {"uv": [9, 12, 10, 12.6], "texture": "#wood_sword"},
				"down": {"uv": [9, 12, 10, 12.6], "texture": "#wood_sword"}
			}
		},
		{
			"name": "guard_6",
			"from": [5, 8, 7.7],
			"to": [6, 10, 8.3],
			"rotation": {"angle": -45, "axis": "z", "origin": [8, 0, 8]},
			"faces": {
				"north": {"uv": [2, 6, 3, 8], "texture": "#wood_sword"},
				"east": {"uv": [2, 6, 2.6, 8], "texture": "#wood_sword"},
				"south": {"uv": [2, 6, 3, 8], "texture": "#wood_sword"},
				"west": {"uv": [2, 6, 2.6, 8], "texture": "#wood_sword"},
				"up": {"uv": [2, 6, 3, 6.6], "texture": "#wood_sword"},
				"down": {"uv": [2, 7, 3, 7.6], "texture": "#wood_sword"}
			}
		},
		{
			"name": "guard_7",
			"from": [4, 9, 7.7],
			"to": [5, 10, 8.3],
			"rotation": {"angle": -45, "axis": "z", "origin": [8, 0, 8]},
			"faces": {
				"north": {"uv": [3, 6, 4, 7], "texture": "#wood_sword"},
				"east": {"uv": [3, 6, 3.6, 7], "texture": "#wood_sword"},
				"south": {"uv": [3, 6, 4, 7], "texture": "#wood_sword"},
				"west": {"uv": [3, 6, 3.6, 7], "texture": "#wood_sword"},
				"up": {"uv": [3, 6, 4, 6.6], "texture": "#wood_sword"},
				"down": {"uv": [3, 6, 4, 6.6], "texture": "#wood_sword"}
			}
		},
		{
			"name": "guard_8",
			"from": [-1, 4, 7.7],
			"to": [0, 5, 8.3],
			"rotation": {"angle": -45, "axis": "z", "origin": [8, 0, 8]},
			"faces": {
				"north": {"uv": [8, 11, 9, 12], "texture": "#wood_sword"},
				"east": {"uv": [8, 11, 8.6, 12], "texture": "#wood_sword"},
				"south": {"uv": [8, 11, 9, 12], "texture": "#wood_sword"},
				"west": {"uv": [8, 11, 8.6, 12], "texture": "#wood_sword"},
				"up": {"uv": [8, 11, 9, 11.6], "texture": "#wood_sword"},
				"down": {"uv": [8, 11, 9, 11.6], "texture": "#wood_sword"}
			}
		},
		{
			"name": "guard_9",
			"from": [3, 8, 7.7],
			"to": [4, 9, 8.3],
			"rotation": {"angle": -45, "axis": "z", "origin": [8, 0, 8]},
			"faces": {
				"north": {"uv": [4, 7, 5, 8], "texture": "#wood_sword"},
				"east": {"uv": [4, 7, 4.6, 8], "texture": "#wood_sword"},
				"south": {"uv": [4, 7, 5, 8], "texture": "#wood_sword"},
				"west": {"uv": [4, 7, 4.6, 8], "texture": "#wood_sword"},
				"up": {"uv": [4, 7, 5, 7.6], "texture": "#wood_sword"},
				"down": {"uv": [4, 7, 5, 7.6], "texture": "#wood_sword"}
			}
		},
		{
			"name": "guard_10",
			"from": [0, 5, 7.7],
			"to": [2, 6, 8.3],
			"rotation": {"angle": -45, "axis": "z", "origin": [8, 0, 8]},
			"faces": {
				"north": {"uv": [6, 10, 8, 11], "texture": "#wood_sword"},
				"east": {"uv": [6, 10, 6.6, 11], "texture": "#wood_sword"},
				"south": {"uv": [6, 10, 8, 11], "texture": "#wood_sword"},
				"west": {"uv": [7, 10, 7.6, 11], "texture": "#wood_sword"},
				"up": {"uv": [6, 10, 8, 10.6], "texture": "#wood_sword"},
				"down": {"uv": [6, 10, 8, 10.6], "texture": "#wood_sword"}
			}
		},
		{
			"name": "guard_11",
			"from": [2, 6, 7.7],
			"to": [3, 8, 8.3],
			"rotation": {"angle": -45, "axis": "z", "origin": [8, 0, 8]},
			"faces": {
				"north": {"uv": [5, 8, 6, 10], "texture": "#wood_sword"},
				"east": {"uv": [5, 8, 5.6, 10], "texture": "#wood_sword"},
				"south": {"uv": [5, 8, 6, 10], "texture": "#wood_sword"},
				"west": {"uv": [5, 8, 5.6, 10], "texture": "#wood_sword"},
				"up": {"uv": [5, 8, 6, 8.6], "texture": "#wood_sword"},
				"down": {"uv": [5, 9, 6, 9.6], "texture": "#wood_sword"}
			}
		},
		{
			"name": "guard_inner_0",
			"from": [2, 5, 7.6],
			"to": [3, 6, 8.4],
			"rotation": {"angle": -45, "axis": "z", "origin": [8, 0, 8]},
			"faces": {
				"north": {"uv": [5, 10, 6, 11], "texture": "#wood_sword"},
				"east": {"uv": [5, 10, 5.8, 11], "texture": "#wood_sword"},
				"south": {"uv": [5, 10, 6, 11], "texture": "#wood_sword"},
				"west": {"uv": [5, 10, 5.8, 11], "texture": "#wood_sword"},
				"up": {"uv": [5, 10, 6, 10.8], "texture": "#wood_sword"},
				"down": {"uv": [5, 10, 6, 10.8], "texture": "#wood_sword"}
			}
		},
		{
			"name": "guard_inner_1",
			"from": [0, 4, 7.6],
			"to": [2, 5, 8.4],
			"rotation": {"angle": -45, "axis": "z", "origin": [8, 0, 8]},
			"faces": {
				"north": {"uv": [6, 11, 8, 12], "texture": "#wood_sword"},
				"east": {"uv": [6, 11, 6.8, 12], "texture": "#wood_sword"},
				"south": {"uv": [6, 11, 8, 12], "rotation": 180, "texture": "#wood_sword"},
				"west": {"uv": [7, 11, 7.8, 12], "texture": "#wood_sword"},
				"up": {"uv": [6, 11, 8, 11.8], "rotation": 180, "texture": "#wood_sword"},
				"down": {"uv": [6, 11, 8, 11.8], "rotation": 180, "texture": "#wood_sword"}
			}
		},
		{
			"name": "guard_inner_2",
			"from": [3, 6, 7.6],
			"to": [4, 8, 8.4],
			"rotation": {"angle": -45, "axis": "z", "origin": [8, 0, 8]},
			"faces": {
				"north": {"uv": [4, 8, 5, 10], "texture": "#wood_sword"},
				"east": {"uv": [4, 8, 4.8, 10], "texture": "#wood_sword"},
				"south": {"uv": [4, 8, 5, 10], "texture": "#wood_sword"},
				"west": {"uv": [4, 8, 4.8, 10], "texture": "#wood_sword"},
				"up": {"uv": [4, 8, 5, 8.8], "texture": "#wood_sword"},
				"down": {"uv": [4, 9, 5, 9.8], "texture": "#wood_sword"}
			}
		},
		{
			"name": "guard_inner_3",
			"from": [-1, 3, 7.6],
			"to": [0, 4, 8.4],
			"rotation": {"angle": -45, "axis": "z", "origin": [8, 0, 8]},
			"faces": {
				"north": {"uv": [8, 12, 9, 13], "texture": "#wood_sword"},
				"east": {"uv": [8, 12, 8.8, 13], "texture": "#wood_sword"},
				"south": {"uv": [8, 12, 9, 13], "texture": "#wood_sword"},
				"west": {"uv": [8, 12, 8.8, 13], "texture": "#wood_sword"},
				"up": {"uv": [8, 12, 9, 12.8], "texture": "#wood_sword"},
				"down": {"uv": [8, 12, 9, 12.8], "texture": "#wood_sword"}
			}
		},
		{
			"name": "guard_inner_4",
			"from": [4, 8, 7.6],
			"to": [5, 9, 8.4],
			"rotation": {"angle": -45, "axis": "z", "origin": [8, 0, 8]},
			"faces": {
				"north": {"uv": [3, 7, 4, 8], "texture": "#wood_sword"},
				"east": {"uv": [3, 7, 3.8, 8], "texture": "#wood_sword"},
				"south": {"uv": [3, 7, 4, 8], "texture": "#wood_sword"},
				"west": {"uv": [3, 7, 3.8, 8], "texture": "#wood_sword"},
				"up": {"uv": [3, 7, 4, 7.8], "texture": "#wood_sword"},
				"down": {"uv": [3, 7, 4, 7.8], "texture": "#wood_sword"}
			}
		},
		{
			"name": "connecter",
			"from": [0, 6, 7.8],
			"to": [2, 8, 8.2],
			"rotation": {"angle": -45, "axis": "z", "origin": [8, 0, 8]},
			"faces": {
				"north": {"uv": [6, 8, 8, 10], "texture": "#wood_sword"},
				"east": {"uv": [6, 8, 6.4, 10], "texture": "#wood_sword"},
				"south": {"uv": [6, 8, 8, 10], "rotation": 90, "texture": "#wood_sword"},
				"west": {"uv": [7, 8, 7.4, 10], "texture": "#wood_sword"},
				"up": {"uv": [6, 9, 8, 9.4], "texture": "#wood_sword"},
				"down": {"uv": [6, 8, 8, 8.4], "texture": "#wood_sword"}
			}
		},
		{
			"name": "villager_base",
			"from": [6.4, 10, 6.8],
			"to": [9.6, 17.2, 9.2],
			"faces": {
				"north": {"uv": [6.5, 9, 8.5, 13.5], "texture": "#farmer"},
				"east": {"uv": [5, 9, 6.5, 13.5], "texture": "#farmer"},
				"south": {"uv": [3, 9, 5, 13.5], "texture": "#farmer"},
				"west": {"uv": [1.5, 9, 3, 13.5], "texture": "#farmer"},
				"up": {"uv": [3, 7.5, 5, 9], "texture": "#farmer"},
				"down": {"uv": [5, 7.5, 7.5, 9], "texture": "#farmer"}
			}
		},
		{
			"name": "villager_head",
			"from": [6.4, 17.2, 6.6],
			"to": [9.6, 21.2, 9.8],
			"faces": {
				"north": {"uv": [7, 4, 9, 6.5], "texture": "#farmer"},
				"east": {"uv": [5, 4, 7, 6.5], "texture": "#farmer"},
				"south": {"uv": [3, 4, 5, 6.5], "texture": "#farmer"},
				"west": {"uv": [1, 4, 3, 6.5], "texture": "#farmer"},
				"up": {"uv": [3, 2, 5, 4], "texture": "#farmer"},
				"down": {"uv": [5, 2, 7, 4], "rotation": 180, "texture": "#farmer"}
			}
		},
		{
			"name": "villager_nose",
			"from": [7.6, 16.8, 9.8],
			"to": [8.4, 18.4, 10.6],
			"faces": {
				"north": {"uv": [0.1, 0.6, 0.4, 1.4], "texture": "#farmer"},
				"east": {"uv": [1.1, 0.6, 1.4, 1.4], "texture": "#farmer"},
				"south": {"uv": [0.6, 0.6, 0.9, 1.4], "texture": "#farmer"},
				"west": {"uv": [1.6, 0.6, 1.9, 1.4], "texture": "#farmer"},
				"up": {"uv": [0.6, 0.1, 0.9, 0.4], "texture": "#farmer"},
				"down": {"uv": [1.1, 0.1, 1.4, 0.3], "texture": "#farmer"}
			}
		},
		{
			"name": "villager_arms",
			"from": [4.8, 13.6, 7],
			"to": [11.2, 16.8, 8.6],
			"rotation": {"angle": -45, "axis": "x", "origin": [8, 16.2, 8.4]},
			"faces": {
				"north": {"uv": [10.5, 10.5, 14.5, 12.5], "texture": "#farmer"},
				"east": {"uv": [14.5, 7.5, 15.5, 9.5], "texture": "#farmer"},
				"south": {"uv": [10.5, 10.5, 14.5, 12.5], "texture": "#farmer"},
				"west": {"uv": [9.5, 7.5, 10.5, 9.5], "texture": "#farmer"},
				"up": {"uv": [10.5, 9.5, 14.4, 10.7], "texture": "#farmer"},
				"down": {"uv": [10.5, 12.5, 14.5, 13.5], "texture": "#farmer"}
			}
		}
	],
	"display": {
		"thirdperson": {
			"rotation": [0, 90, -90],
			"translation": [0, 0.75, -2],
			"scale": [1, 1, 1]
		},
		"firstperson": {
			"rotation": [0, 225, -15],
			"translation": [1.13, 3.2, 1.13],
			"scale": [1.6, 1.6, 1.6]
		},
		"ground": {
			"translation": [0, 2, 0],
			"scale": [2, 2, 2]
		},
		"gui": {
			"rotation": [-45, 135, -45],
			"translation": [2, -2, 0],
			"scale": [1.5, 1.5, 1.5]
		},
		"head": {
			"rotation": [0, 180, 0],
			"translation": [0, 14.25, 0]
		},
		"fixed": {
			"rotation": [0, -180, -45],
			"translation": [2, -2.25, 0],
			"scale": [2, 2, 2]
		}
	}
}